HuhuSeg-0.6.1.dist-info/DESCRIPTION.rst
HuhuSeg-0.6.1.dist-info/METADATA
HuhuSeg-0.6.1.dist-info/RECORD
HuhuSeg-0.6.1.dist-info/WHEEL
HuhuSeg-0.6.1.dist-info/metadata.json
HuhuSeg-0.6.1.dist-info/top_level.txt
huhu_seg/__init__.py
huhu_seg/bow.py
huhu_seg/clustering.py
huhu_seg/hmm.py
huhu_seg/hotspot.py
huhu_seg/huhu_seg.py
huhu_seg/segmentor.py
huhu_seg/simhash.py
huhu_seg/textrank.py
huhu_seg/tfidf.py
huhu_seg/topic.py
huhu_seg/trie.py
huhu_seg/lexicon/dict.segd
huhu_seg/lexicon/nr.segd
huhu_seg/lexicon/nr.tr.segd
huhu_seg/lexicon/stop_words.segd
huhu_seg/lexicon/wiki_idf_986891.segd
