Metadata-Version: 2.0
Name: HuhuSeg
Version: 0.6.1
Summary: Simple Chinese segmentator, keywords extractor and other examples
Home-page: https://github.com/Colearo/HuhuSeg
Author: Kechen Lu
Author-email: colearolu@icloud.com
License: GNU General Public License v3 (GPLv3)
Keywords: chinese-segmentation keywords-extraction nlp
Platform: UNKNOWN
Classifier: Development Status :: 3 - Alpha
Classifier: Intended Audience :: Developers
Classifier: Topic :: Scientific/Engineering :: Information Analysis
Classifier: License :: OSI Approved :: GNU General Public License v3 (GPLv3)
Classifier: Programming Language :: Python :: 3.4
Classifier: Programming Language :: Python :: 3.5
Classifier: Programming Language :: Python :: 3.6
Requires-Dist: numpy
